rayyan/__init__.py
rayyan/admin.py
rayyan/conf.py
rayyan/duplicates.py
rayyan/errors.py
rayyan/highlight.py
rayyan/mylib.py
rayyan/notes.py
rayyan/paths.py
rayyan/request.py
rayyan/review.py
rayyan/review_access.py
rayyan/search.py
rayyan/third_party_auth.py
rayyan/types.py
rayyan/user.py
rayyan/reviews/__init__.py
rayyan/reviews/ai_screeners.py
rayyan/reviews/articles.py
rayyan/reviews/base.py
rayyan/reviews/criteria.py
rayyan/reviews/customizations.py
rayyan/reviews/exports.py
rayyan/reviews/filters.py
rayyan/reviews/fulltext.py
rayyan/reviews/importers.py
rayyan/reviews/metadata.py
rayyan/reviews/questions.py
rayyan/reviews/samples.py
rayyan_sdk-1.0rc15.dist-info/LICENSE
rayyan_sdk-1.0rc15.dist-info/METADATA
rayyan_sdk-1.0rc15.dist-info/WHEEL
rayyan_sdk-1.0rc15.dist-info/top_level.txt
rayyan_sdk-1.0rc15.dist-info/RECORD
