Metadata-Version: 2.1
Name: rayyan-sdk
Version: 1.0rc15
Summary: A Python SDK for Rayyan APIs
Home-page: https://github.com/rayyansys/rayyan-python-sdk
Author: Rayyan Systems, Inc.
Author-email: support@rayyan.ai
License: MIT
Platform: UNKNOWN
Classifier: Environment :: Web Environment
Classifier: Intended Audience :: Developers
Classifier: License :: OSI Approved :: MIT License
Classifier: Operating System :: OS Independent
Classifier: Programming Language :: Python
Classifier: Programming Language :: Python :: 3
Classifier: Programming Language :: Python :: 3 :: Only
Classifier: Programming Language :: Python :: 3.7
Classifier: Programming Language :: Python :: 3.8
Classifier: Programming Language :: Python :: 3.9
Classifier: Topic :: Internet :: WWW/HTTP
Classifier: Topic :: Internet :: WWW/HTTP :: Dynamic Content
Requires-Python: >=3.7
Requires-Dist: requests>=2
Requires-Dist: requests-toolbelt>=1
